klink_sdk/__init__.py
klinkfinance_sdk/__init__.py
klinkfinance_sdk/sdk.py
klinkfinance_sdk/__pycache__/__init__.cpython-314.pyc
klinkfinance_sdk/__pycache__/sdk.cpython-314.pyc
klinkfinance_sdk/core/__init__.py
klinkfinance_sdk/core/advertiser_client.py
klinkfinance_sdk/core/http_client.py
klinkfinance_sdk/core/publisher_client.py
klinkfinance_sdk/core/__pycache__/__init__.cpython-314.pyc
klinkfinance_sdk/core/__pycache__/advertiser_client.cpython-314.pyc
klinkfinance_sdk/core/__pycache__/http_client.cpython-314.pyc
klinkfinance_sdk/core/__pycache__/publisher_client.cpython-314.pyc
klinkfinance_sdk/types/__init__.py
klinkfinance_sdk/types/config.py
klinkfinance_sdk/types/exceptions.py
klinkfinance_sdk/types/__pycache__/__init__.cpython-314.pyc
klinkfinance_sdk/types/__pycache__/config.cpython-314.pyc
klinkfinance_sdk/types/__pycache__/exceptions.cpython-314.pyc
klinkfinance_sdk/utils/__init__.py
klinkfinance_sdk/utils/logger.py
klinkfinance_sdk/utils/validator.py
klinkfinance_sdk/utils/__pycache__/__init__.cpython-314.pyc
klinkfinance_sdk/utils/__pycache__/logger.cpython-314.pyc
klinkfinance_sdk/utils/__pycache__/validator.cpython-314.pyc
klinkfinance_sdk-1.0.1.dist-info/METADATA
klinkfinance_sdk-1.0.1.dist-info/WHEEL
klinkfinance_sdk-1.0.1.dist-info/top_level.txt
klinkfinance_sdk-1.0.1.dist-info/RECORD
