Metadata-Version: 2.4
Name: klinkfinance-sdk
Version: 1.0.1
Summary: Official Python SDK for the Klink Finance platform - Publisher and Advertiser APIs
Home-page: https://github.com/KlinkFinance/publisher-sdk
Author: Klink Finance
Author-email: Klink Finance <dev@klink.finance>
License: MIT
Project-URL: Homepage, https://github.com/KlinkFinance/publisher-sdk
Project-URL: Documentation, https://github.com/KlinkFinance/publisher-sdk/blob/develop/README.md
Project-URL: Repository, https://github.com/KlinkFinance/publisher-sdk
Project-URL: Issues, https://github.com/KlinkFinance/publisher-sdk/issues
Keywords: klink,finance,sdk,publisher,advertiser,api,crypto
Classifier: Development Status :: 5 - Production/Stable
Classifier: Intended Audience :: Developers
Classifier: Topic :: Software Development :: Libraries :: Python Modules
Classifier: License :: OSI Approved :: MIT License
Classifier: Programming Language :: Python :: 3
Classifier: Programming Language :: Python :: 3.8
Classifier: Programming Language :: Python :: 3.9
Classifier: Programming Language :: Python :: 3.10
Classifier: Programming Language :: Python :: 3.11
Classifier: Programming Language :: Python :: 3.12
Requires-Python: >=3.8
Requires-Dist: requests>=2.25.0
Provides-Extra: dev
Requires-Dist: pytest>=6.0; extra == "dev"
Requires-Dist: pytest-cov>=2.0; extra == "dev"
Requires-Dist: pytest-mock>=3.10.0; extra == "dev"
Requires-Dist: black>=21.0; extra == "dev"
Requires-Dist: mypy>=0.900; extra == "dev"
Requires-Dist: pylint>=2.0; extra == "dev"
Dynamic: author
Dynamic: home-page
Dynamic: requires-python
